brainrot/__init__.py
brainrot/core.py
py_brainrot-0.1.4.dist-info/LICENSE
py_brainrot-0.1.4.dist-info/METADATA
py_brainrot-0.1.4.dist-info/WHEEL
py_brainrot-0.1.4.dist-info/top_level.txt
py_brainrot-0.1.4.dist-info/RECORD
