Metadata-Version: 2.1
Name: py_brainrot
Version: 0.1.4
Summary: The module that lets Gen Z grind Sigma code with max rizz
Author-email: WhiteMCWizard <jweiss@whitemcwizard.nl>
License: MIT License
Project-URL: Homepage, https://github.com/WhiteMCWizard/py_brainrot
Project-URL: Bug Tracker, https://github.com/WhiteMCWizard/py_brainrot/issues
Keywords: gen-z,slang,built-ins,wrapper
Classifier: Programming Language :: Python :: 3
Classifier: License :: OSI Approved :: MIT License
Classifier: Operating System :: OS Independent
Requires-Python: >=3.7
License-File: LICENSE
